README.rst
setup.py
longtask/__init__.py
longtask/storage.py
longtask/task.py
longtask/tests.py
longtask/utils.py
longtask/widgets.py
longtask.egg-info/PKG-INFO
longtask.egg-info/SOURCES.txt
longtask.egg-info/dependency_links.txt
longtask.egg-info/requires.txt
longtask.egg-info/top_level.txt