Metadata-Version: 1.1
Name: longtask
Version: 0.1.1
Summary: Long task runner.
Home-page: https://github.com/konradhalas/longtask
Author: Konrad Hałas
Author-email: halas.konrad@gmail.com
License: UNKNOWN
Platform: UNKNOWN
Classifier: Intended Audience :: Developers
Classifier: License :: OSI Approved :: Apache Software License
